README.txt
setup.cfg
setup.py
docs/HISTORY.txt
pcommerce/__init__.py
pcommerce.shipment.parcel.egg-info/PKG-INFO
pcommerce.shipment.parcel.egg-info/SOURCES.txt
pcommerce.shipment.parcel.egg-info/dependency_links.txt
pcommerce.shipment.parcel.egg-info/entry_points.txt
pcommerce.shipment.parcel.egg-info/namespace_packages.txt
pcommerce.shipment.parcel.egg-info/not-zip-safe
pcommerce.shipment.parcel.egg-info/requires.txt
pcommerce.shipment.parcel.egg-info/top_level.txt
pcommerce/shipment/__init__.py
pcommerce/shipment/parcel/__init__.py
pcommerce/shipment/parcel/configure.zcml
pcommerce/shipment/parcel/data.py
pcommerce/shipment/parcel/interfaces.py
pcommerce/shipment/parcel/plugin.py
pcommerce/shipment/parcel/browser/__init__.py
pcommerce/shipment/parcel/browser/base.py
pcommerce/shipment/parcel/browser/configure.zcml
pcommerce/shipment/parcel/browser/confirmation.pt
pcommerce/shipment/parcel/browser/confirmation.py
pcommerce/shipment/parcel/browser/icon.png
pcommerce/shipment/parcel/browser/logo.png
pcommerce/shipment/parcel/browser/overview.pt
pcommerce/shipment/parcel/browser/overview.py
pcommerce/shipment/parcel/browser/shipment.pt
pcommerce/shipment/parcel/browser/shipment.py
pcommerce/shipment/parcel/i18n/pcommerce-de.po
pcommerce/shipment/parcel/i18n/pcommerce-nl.po
pcommerce/shipment/parcel/i18n/pcommerce.pot
pcommerce/shipment/parcel/profiles/default/metadata.xml
pcommerce/shipment/parcel/profiles/default/propertiestool.xml