Metadata-Version: 1.0
Name: pcommerce.shipment.parcel
Version: 1.0b2
Summary: A parcel shipment plugin for PCommerce
Home-page: http://raptus.com
Author: Jan Boehler
Author-email: jboehler@raptus.com
License: GPL
Platform: UNKNOWN
Classifier: Programming Language :: Python
Classifier: Topic :: Software Development :: Libraries :: Python Modules
